cgse_common/__init__.py
cgse_common/settings.yaml
egse/bits.py
egse/calibration.py
egse/command.py
egse/config.py
egse/control.py
egse/decorators.py
egse/device.py
egse/env.py
egse/exceptions.py
egse/hk.py
egse/metrics.py
egse/mixin.py
egse/monitoring.py
egse/observer.py
egse/obsid.py
egse/persistence.py
egse/plugin.py
egse/process.py
egse/protocol.py
egse/proxy.py
egse/reload.py
egse/resource.py
egse/response.py
egse/services.py
egse/services.yaml
egse/settings.py
egse/settings.yaml
egse/setup.py
egse/state.py
egse/system.py
egse/version.py
egse/zmq_ser.py
cgse_common-2025.0.9.dist-info/METADATA
cgse_common-2025.0.9.dist-info/WHEEL
cgse_common-2025.0.9.dist-info/entry_points.txt
cgse_common-2025.0.9.dist-info/RECORD
