Metadata-Version: 2.4
Name: cgse-common
Version: 2025.0.9
Summary: Software framework to support hardware testing
Author: IVS KU Leuven
Maintainer-email: Rik Huygen <rik.huygen@kuleuven.be>, Sara Regibo <sara.regibo@kuleuven.be>
License-Expression: MIT
Keywords: CGSE,Common-EGSE,hardware testing,software framework
Requires-Python: >=3.9
Requires-Dist: click>=8.1.8
Requires-Dist: deepdiff>=8.1.1
Requires-Dist: distro>=1.9.0
Requires-Dist: gitpython>=3.1.44
Requires-Dist: numpy==1.22.4
Requires-Dist: pandas>=1.5.1
Requires-Dist: pip>=24.3.1
Requires-Dist: prometheus-client>=0.21.1
Requires-Dist: psutil>=6.1.1
Requires-Dist: pyyaml>=6.0.2
Requires-Dist: pyzmq==23.2.1
Requires-Dist: rich>=13.9.4
